dios/__init__.py
dios/base.py
dios/dios.py
dios/indexer.py
dios/lib.py
dios/operators.py
dios/pandas_bridge.py
dios-0.6.0.dist-info/METADATA
dios-0.6.0.dist-info/WHEEL
dios-0.6.0.dist-info/top_level.txt
dios-0.6.0.dist-info/RECORD
