Metadata-Version: 2.1
Name: dios
Version: 0.6.0
Summary: Dictionary of Series - a kind of pandas extension
Home-page: https://git.ufz.de/rdm/dios
Author: Bert Palm
Author-email: bert.palm@ufz.de
License: GPLv3
Platform: UNKNOWN
Requires-Dist: pandas
